assemblerflow/__init__.py
assemblerflow/assemblerflow.py
assemblerflow/nextflow.config
assemblerflow/profiles.config
assemblerflow/bin/final_POST.sh
assemblerflow/bin/merge_json.py
assemblerflow/bin/parse_true_coverage.py
assemblerflow/bin/prepare_reports.py
assemblerflow/bin/report_POST.sh
assemblerflow/bin/set_dotfiles.sh
assemblerflow/bin/startup_POST.sh
assemblerflow/generator/__init__.py
assemblerflow/generator/engine.py
assemblerflow/generator/error_handling.py
assemblerflow/generator/footer_skeleton.py
assemblerflow/generator/header_skeleton.py
assemblerflow/generator/pipeline_parser.py
assemblerflow/generator/process.py
assemblerflow/generator/process_details.py
assemblerflow/generator/recipe.py
assemblerflow/generator/components/__init__.py
assemblerflow/generator/components/annotation.py
assemblerflow/generator/components/assembly.py
assemblerflow/generator/components/assembly_processing.py
assemblerflow/generator/components/distance_estimation.py
assemblerflow/generator/components/downloads.py
assemblerflow/generator/components/mapping.py
assemblerflow/generator/components/mlst.py
assemblerflow/generator/components/reads_quality_control.py
assemblerflow/generator/components/typing.py
assemblerflow/generator/templates/Helper.groovy
assemblerflow/generator/templates/abricate.nf
assemblerflow/generator/templates/assembly_mapping.nf
assemblerflow/generator/templates/check_coverage.nf
assemblerflow/generator/templates/chewbbaca.nf
assemblerflow/generator/templates/compiler_channels.txt
assemblerflow/generator/templates/containers.config
assemblerflow/generator/templates/fastqc.nf
assemblerflow/generator/templates/fastqc_trimmomatic.nf
assemblerflow/generator/templates/init.nf
assemblerflow/generator/templates/integrity_coverage.nf
assemblerflow/generator/templates/mapping_patlas.nf
assemblerflow/generator/templates/mash_dist.nf
assemblerflow/generator/templates/mash_screen.nf
assemblerflow-1.1.0.post3.dist-info/METADATA
assemblerflow-1.1.0.post3.dist-info/RECORD
assemblerflow-1.1.0.post3.dist-info/WHEEL
assemblerflow-1.1.0.post3.dist-info/entry_points.txt
assemblerflow-1.1.0.post3.dist-info/top_level.txt
