Metadata-Version: 2.1
Name: assemblerflow
Version: 1.1.0.post3
Summary: A Nextflow pipeline assembler for genomics. Pick your modules. Assemble them. Run the pipeline.
Home-page: https://github.com/ODiogoSilva/assemblerflow
Author: Diogo N Silva
Author-email: o.diogosilva@gmail.com
License: GPL3
Platform: UNKNOWN
Requires-Dist: argparse
Requires-Dist: jinja2
